auditor_apel_plugin/__init__.py
auditor_apel_plugin/config.py
auditor_apel_plugin/core.py
auditor_apel_plugin/message.py
auditor_apel_plugin/publish.py
auditor_apel_plugin/republish.py
auditor_apel_plugin/utility.py
auditor_apel_plugin-0.10.0.dist-info/licenses/LICENSE
auditor_apel_plugin-0.10.0.dist-info/METADATA
auditor_apel_plugin-0.10.0.dist-info/WHEEL
auditor_apel_plugin-0.10.0.dist-info/entry_points.txt
auditor_apel_plugin-0.10.0.dist-info/top_level.txt
auditor_apel_plugin-0.10.0.dist-info/RECORD
