Metadata-Version: 2.4
Name: auditor_apel_plugin
Version: 0.10.0
Summary: AUDITOR plugin for sending accounting data to APEL
Requires-Python: >=3.9
License-File: LICENSE
Requires-Dist: python-auditor==0.10.0
Requires-Dist: cryptography==45.0.5
Requires-Dist: pyyaml==6.0.2
Requires-Dist: pydantic==2.11.7
Requires-Dist: argo-ams-library==1.0.0
Provides-Extra: style
Requires-Dist: black==25.1.0; extra == "style"
Requires-Dist: ruff==0.12.7; extra == "style"
Provides-Extra: tests
Requires-Dist: pytest==8.4.1; extra == "tests"
Requires-Dist: pytest-cov==6.2.1; extra == "tests"
Requires-Dist: mypy==1.17.1; extra == "tests"
Requires-Dist: types-pyyaml==6.0.12.20250516; extra == "tests"
Provides-Extra: build
Requires-Dist: build==1.3.0; extra == "build"
Requires-Dist: setuptools==80.9.0; extra == "build"
Dynamic: license-file
